qif/__init__.py
qif/__init__.pyi
qif/_qif.cpython-311-x86_64-linux-gnu.so
qif/lp.pyi
qif/probab.pyi
qif/refinement.pyi
qif/typing.py
qif/utility.pyi
qif/.libs/libarmadillo-91e09440.so.10.2.0
qif/.libs/libgfortran-83c28eba.so.5.0.0
qif/.libs/libgmp-afefff82.so.10.4.1
qif/.libs/libgsl-b64c76bc.so.23.1.0
qif/.libs/libgslcblas-cd2c2030.so.0.0.0
qif/.libs/libmp++-ec6e60c4.so.16.0
qif/.libs/libopenblas_sandybridgep-r0-df648e6f.3.20.so
qif/.libs/libortools-262da40d.so
qif/.libs/libqif-2290b374.so
qif/.libs/libquadmath-2284e583.so.0.0.0
qif/channel/__init__.py
qif/channel/__init__.pyi
qif/channel/compose.pyi
qif/measure/__init__.py
qif/measure/__init__.pyi
qif/measure/bayes_risk.pyi
qif/measure/bayes_vuln.pyi
qif/measure/d_privacy.pyi
qif/measure/g_vuln.pyi
qif/measure/guessing.pyi
qif/measure/l_risk.pyi
qif/measure/pred_risk.pyi
qif/measure/pred_vuln.pyi
qif/measure/shannon.pyi
qif/mechanism/__init__.py
qif/mechanism/__init__.pyi
qif/mechanism/bayes_risk.pyi
qif/mechanism/bayes_vuln.pyi
qif/mechanism/d_privacy.pyi
qif/mechanism/g_vuln.pyi
qif/mechanism/geo_ind.pyi
qif/mechanism/l_risk.pyi
qif/mechanism/shannon.pyi
qif/metric/__init__.py
qif/metric/__init__.pyi
qif/metric/optimize.pyi
qif-1.2.4.dist-info/METADATA
qif-1.2.4.dist-info/WHEEL
qif-1.2.4.dist-info/top_level.txt
qif-1.2.4.dist-info/RECORD
